{
  "spec_version": "1",
  "task_id": "t0022_modify_dsgc_channel_testbed",
  "command": "uv run python -u -m tasks.t0022_modify_dsgc_channel_testbed.code.plot_tuning_curve",
  "exit_code": 0,
  "duration_seconds": 2.625,
  "started_at": "2026-04-21T00:10:58Z",
  "completed_at": "2026-04-21T00:11:01Z",
  "working_directory": "C:\\Users\\md1avn\\Documents\\GitHub\\neuron-channels-worktrees\\t0022_modify_dsgc_channel_testbed",
  "stdout_file": "019_20260421T001058Z_uv-run-python.stdout.txt",
  "stderr_file": "019_20260421T001058Z_uv-run-python.stderr.txt",
  "stdout_lines": 1,
  "stderr_lines": 0,
  "truncated": false
}
