{
  "spec_version": "1",
  "task_id": "t0002_literature_survey_dsgc_compartmental_models",
  "command": "uv run python -u -m arf.scripts.utils.doi_to_slug 10.1113/jphysiol.1965.sp007638",
  "exit_code": 0,
  "duration_seconds": 0.278,
  "started_at": "2026-04-18T23:38:54Z",
  "completed_at": "2026-04-18T23:38:55Z",
  "working_directory": "C:\\Users\\md1avn\\Documents\\GitHub\\neuron-channels-worktrees\\t0002_literature_survey_dsgc_compartmental_models",
  "stdout_file": "003_20260418T233854Z_uv-run-python.stdout.txt",
  "stderr_file": "003_20260418T233854Z_uv-run-python.stderr.txt",
  "stdout_lines": 1,
  "stderr_lines": 0,
  "truncated": false
}
